odoo/addons/project_category/README.rst
odoo/addons/project_category/__init__.py
odoo/addons/project_category/__manifest__.py
odoo/addons/project_category/i18n/ca.po
odoo/addons/project_category/i18n/de.po
odoo/addons/project_category/i18n/es.po
odoo/addons/project_category/i18n/he.po
odoo/addons/project_category/i18n/project_category.pot
odoo/addons/project_category/models/__init__.py
odoo/addons/project_category/models/project_project.py
odoo/addons/project_category/models/project_task.py
odoo/addons/project_category/models/project_type.py
odoo/addons/project_category/readme/CONTRIBUTORS.rst
odoo/addons/project_category/readme/DESCRIPTION.rst
odoo/addons/project_category/readme/USAGE.rst
odoo/addons/project_category/security/ir.model.access.csv
odoo/addons/project_category/static/description/icon.png
odoo/addons/project_category/static/description/index.html
odoo/addons/project_category/tests/__init__.py
odoo/addons/project_category/tests/test_project_category.py
odoo/addons/project_category/views/project_project_views.xml
odoo/addons/project_category/views/project_task_views.xml
odoo/addons/project_category/views/project_type_views.xml
odoo13_addon_project_category-13.0.1.2.0.dist-info/METADATA
odoo13_addon_project_category-13.0.1.2.0.dist-info/WHEEL
odoo13_addon_project_category-13.0.1.2.0.dist-info/top_level.txt
odoo13_addon_project_category-13.0.1.2.0.dist-info/RECORD
